kinto_megaphone/__init__.py
kinto_megaphone/heartbeat.py
kinto_megaphone/listeners.py
kinto_megaphone/megaphone.py
kinto_megaphone-0.5.0.dist-info/LICENSE
kinto_megaphone-0.5.0.dist-info/METADATA
kinto_megaphone-0.5.0.dist-info/WHEEL
kinto_megaphone-0.5.0.dist-info/top_level.txt
kinto_megaphone-0.5.0.dist-info/RECORD
