Metadata-Version: 2.1
Name: kinto-megaphone
Version: 0.5.0
Summary: Send global broadcast messages to Megaphone on changes
Home-page: https://github.com/glasserc/kinto_megaphone
Author: Ethan Glasser-Camp
Author-email: eglassercamp@mozilla.com
License: Apache License (2.0)
Keywords: kinto plugin
Platform: UNKNOWN
Classifier: Programming Language :: Python
Classifier: Programming Language :: Python :: 3.6
Classifier: Programming Language :: Python :: 3.7
Classifier: Topic :: Internet :: WWW/HTTP
Classifier: Topic :: Internet :: WWW/HTTP :: WSGI :: Application
Classifier: License :: OSI Approved :: Apache Software License
Requires-Dist: kinto (>=10.1.1)
Requires-Dist: kinto-changes (>=1.3.0)
Requires-Dist: requests
